ecmwfspec-0.0.6.dist-info/METADATA
ecmwfspec-0.0.6.dist-info/WHEEL
ecmwfspec-0.0.6.dist-info/entry_points.txt
ecmwfspec/__init__.py
ecmwfspec/core.py
ecmwfspec/ecfs_wrapper.py
ecmwfspec/tests/__init__.py
ecmwfspec/tests/conftest.py
ecmwfspec/tests/test_open_dataset.py
ecmwfspec/xr_accessor.py
ecmwfspec-0.0.6.dist-info/RECORD
