Metadata-Version: 2.1
Name: ecmwfspec
Version: 0.0.6
Summary: fsspec implementation for ECMWF File Storage System
Project-URL: Homepage, https://github.com/observingClouds/ecmwfspec
Requires-Dist: fsspec
Requires-Dist: dask
Requires-Dist: universal-pathlib
Requires-Dist: typing_extensions; python_version < "3.11"
Requires-Dist: xarray<=2024.11.0
Provides-Extra: tests
Requires-Dist: mock; extra == "tests"
Requires-Dist: pre-commit; extra == "tests"
Requires-Dist: netCDF4; extra == "tests"
Requires-Dist: numpy; extra == "tests"
Requires-Dist: pandas; extra == "tests"
Requires-Dist: xarray; extra == "tests"
Requires-Dist: zarr<3.0.0; extra == "tests"
Requires-Dist: pytest; extra == "tests"
Requires-Dist: pytest-cov; extra == "tests"
